tax/__init__.py
tax/config.py
tax/evals/__init__.py
tax/evals/base.py
tax/evals/class_eval.py
tax/evals/lang_eval.py
tax/evals/losses.py
tax/examples/__init__.py
tax/examples/bin/download_lra_data.sh
tax/examples/bin/run_lm.sh
tax/examples/bin/run_lra.sh
tax/examples/configs/imdb.yaml
tax/examples/configs/lm.yaml
tax/examples/gemma/__init__.py
tax/examples/gemma/exp.py
tax/examples/gemma/gemma.py
tax/examples/gemma/lm_dp.py
tax/examples/gemma/task.py
tax/examples/lra/__init__.py
tax/examples/lra/exp.py
tax/examples/lra/lra_dp.py
tax/examples/lra/lra_tok.py
tax/examples/lra/model/__init__.py
tax/examples/lra/model/attention.py
tax/examples/lra/model/lra_enc.py
tax/examples/lra/model/task.py
tax/examples/utils.py
tax/lr_schedules.py
tax/train/__init__.py
tax/train/dfsp_jax.py
tax/train/jax_single_host.py
tax/train/utils.py
tax_dp-0.1.1.dist-info/METADATA
tax_dp-0.1.1.dist-info/WHEEL
tax_dp-0.1.1.dist-info/entry_points.txt
tax_dp-0.1.1.dist-info/licenses/LICENSE
tax_dp-0.1.1.dist-info/RECORD
