Metadata-Version: 2.1
Name: tax-dp
Version: 0.1.1
Summary: A fully sharded data parallel trainer for jax
Author-Email: Rares Dolga <rares.dolga.16@ucl.ac.uk>
License: MIT
Requires-Python: >=3.10
Requires-Dist: jax[cuda12]==0.4.31
Requires-Dist: tqdm==4.66.2
Requires-Dist: wandb==0.17.2
Requires-Dist: black>=24.8.0
Requires-Dist: flax==0.8.4
Requires-Dist: orbax-checkpoint==0.6.4
Requires-Dist: matplotlib>=3.9.1
Requires-Dist: pip>=24.2
Requires-Dist: jaxtyping>=0.2.34
Requires-Dist: torch>=2.4.1
Requires-Dist: transformers>=4.45.1
Requires-Dist: datasets>=2.19.2
